[
    {
        "overriddencreatedon":  null,
        "description":  null,
        "timezoneruleversionnumber":  null,
        "componentidunique":  "de9f1d1b-f5e4-4634-8a29-98ff31bb66de",
        "promptingbehavior":  0,
        "_owninguser_value":  "d431eaf0-ead8-f011-8543-002248384659",
        "iscustomizable":  {
                               "Value":  true,
                               "CanBeChanged":  true,
                               "ManagedPropertyLogicalName":  "iscustomizableanddeletable"
                           },
        "overwritetime":  "1900-01-01T00:00:00Z",
        "versionnumber":  2534906,
        "_customconnectorid_value":  null,
        "connectionparametersetconfig":  null,
        "importsequencenumber":  null,
        "_modifiedonbehalfby_value":  "4e8c871e-1ed9-f011-8543-002248384659",
        "connectionreferenceid":  "b05841b8-db34-46d7-a25d-09c344758722",
        "_createdby_value":  "d431eaf0-ead8-f011-8543-002248384659",
        "componentstate":  0,
        "connectionreferencedisplayname":  "Mail",
        "ismanaged":  true,
        "_createdonbehalfby_value":  "4e8c871e-1ed9-f011-8543-002248384659",
        "_modifiedby_value":  "d431eaf0-ead8-f011-8543-002248384659",
        "_owningbusinessunit_value":  "e22aeaf0-ead8-f011-8543-002248384659",
        "connectorid":  "/providers/Microsoft.PowerApps/apis/shared_sendmail",
        "solutionid":  "60202ef0-9d92-427f-996d-27259e5eba15",
        "@odata.etag":  "W/\"2534906\"",
        "_ownerid_value":  "d431eaf0-ead8-f011-8543-002248384659",
        "statecode":  0,
        "connectionid":  null,
        "_owningteam_value":  null,
        "connectionparametersconfig":  null,
        "modifiedon":  "2025-12-19T12:15:24Z",
        "connectionreferencelogicalname":  "msdynce_sharedsendmail_9f42e",
        "utcconversiontimezonecode":  null,
        "statuscode":  1,
        "createdon":  "2025-12-19T12:15:24Z"
    },
    {
        "overriddencreatedon":  null,
        "description":  null,
        "timezoneruleversionnumber":  null,
        "componentidunique":  "6885074a-6652-4cbb-8b83-37c7f5471990",
        "promptingbehavior":  0,
        "_owninguser_value":  "d431eaf0-ead8-f011-8543-002248384659",
        "iscustomizable":  {
                               "Value":  true,
                               "CanBeChanged":  true,
                               "ManagedPropertyLogicalName":  "iscustomizableanddeletable"
                           },
        "overwritetime":  "1900-01-01T00:00:00Z",
        "versionnumber":  2534905,
        "_customconnectorid_value":  null,
        "connectionparametersetconfig":  null,
        "importsequencenumber":  null,
        "_modifiedonbehalfby_value":  "4e8c871e-1ed9-f011-8543-002248384659",
        "connectionreferenceid":  "2c4864c0-6473-4f7b-9bf0-13ce5e5d876a",
        "_createdby_value":  "d431eaf0-ead8-f011-8543-002248384659",
        "componentstate":  0,
        "connectionreferencedisplayname":  "Microsoft Dataverse",
        "ismanaged":  true,
        "_createdonbehalfby_value":  "4e8c871e-1ed9-f011-8543-002248384659",
        "_modifiedby_value":  "d431eaf0-ead8-f011-8543-002248384659",
        "_owningbusinessunit_value":  "e22aeaf0-ead8-f011-8543-002248384659",
        "connectorid":  "/providers/Microsoft.PowerApps/apis/shared_commondataserviceforapps",
        "solutionid":  "60202ef0-9d92-427f-996d-27259e5eba15",
        "@odata.etag":  "W/\"2534905\"",
        "_ownerid_value":  "d431eaf0-ead8-f011-8543-002248384659",
        "statecode":  0,
        "connectionid":  null,
        "_owningteam_value":  null,
        "connectionparametersconfig":  null,
        "modifiedon":  "2025-12-19T12:15:23Z",
        "connectionreferencelogicalname":  "msdynce_sharedcommondataserviceforapps_cfc03",
        "utcconversiontimezonecode":  null,
        "statuscode":  1,
        "createdon":  "2025-12-19T12:15:23Z"
    },
    {
        "overriddencreatedon":  null,
        "description":  null,
        "timezoneruleversionnumber":  null,
        "componentidunique":  "4ff86a0f-a04d-4cc0-ae96-80015b73bab3",
        "promptingbehavior":  0,
        "_owninguser_value":  "358958c0-52b4-4386-8edd-e9b07d4af6d3",
        "iscustomizable":  {
                               "Value":  true,
                               "CanBeChanged":  true,
                               "ManagedPropertyLogicalName":  "iscustomizableanddeletable"
                           },
        "overwritetime":  "1900-01-01T00:00:00Z",
        "versionnumber":  1028070,
        "_customconnectorid_value":  null,
        "connectionparametersetconfig":  null,
        "importsequencenumber":  null,
        "_modifiedonbehalfby_value":  null,
        "connectionreferenceid":  "800b143a-79b2-47cd-9c62-33b9f09ec163",
        "_createdby_value":  "358958c0-52b4-4386-8edd-e9b07d4af6d3",
        "componentstate":  0,
        "connectionreferencedisplayname":  "Dataverse",
        "ismanaged":  true,
        "_createdonbehalfby_value":  null,
        "_modifiedby_value":  "358958c0-52b4-4386-8edd-e9b07d4af6d3",
        "_owningbusinessunit_value":  "e22aeaf0-ead8-f011-8543-002248384659",
        "connectorid":  "/providers/Microsoft.PowerApps/apis/shared_commondataserviceforapps",
        "solutionid":  "0ad90b79-6955-426e-b85f-5194a0361eb2",
        "@odata.etag":  "W/\"1028070\"",
        "_ownerid_value":  "358958c0-52b4-4386-8edd-e9b07d4af6d3",
        "statecode":  0,
        "connectionid":  null,
        "_owningteam_value":  null,
        "connectionparametersconfig":  null,
        "modifiedon":  "2025-12-14T17:13:19Z",
        "connectionreferencelogicalname":  "msdyn_Dataverse",
        "utcconversiontimezonecode":  null,
        "statuscode":  1,
        "createdon":  "2025-12-14T17:13:19Z"
    },
    {
        "overriddencreatedon":  null,
        "description":  null,
        "timezoneruleversionnumber":  null,
        "componentidunique":  "e0078794-3a96-4ee6-ab8a-898f88b65a58",
        "promptingbehavior":  0,
        "_owninguser_value":  "d431eaf0-ead8-f011-8543-002248384659",
        "iscustomizable":  {
                               "Value":  true,
                               "CanBeChanged":  true,
                               "ManagedPropertyLogicalName":  "iscustomizableanddeletable"
                           },
        "overwritetime":  "1900-01-01T00:00:00Z",
        "versionnumber":  2534900,
        "_customconnectorid_value":  null,
        "connectionparametersetconfig":  null,
        "importsequencenumber":  null,
        "_modifiedonbehalfby_value":  "4e8c871e-1ed9-f011-8543-002248384659",
        "connectionreferenceid":  "da9f55d7-7dc2-4d06-8ebb-467d76d45459",
        "_createdby_value":  "d431eaf0-ead8-f011-8543-002248384659",
        "componentstate":  0,
        "connectionreferencedisplayname":  "Mail",
        "ismanaged":  true,
        "_createdonbehalfby_value":  "4e8c871e-1ed9-f011-8543-002248384659",
        "_modifiedby_value":  "d431eaf0-ead8-f011-8543-002248384659",
        "_owningbusinessunit_value":  "e22aeaf0-ead8-f011-8543-002248384659",
        "connectorid":  "/providers/Microsoft.PowerApps/apis/shared_sendmail",
        "solutionid":  "60202ef0-9d92-427f-996d-27259e5eba15",
        "@odata.etag":  "W/\"2534900\"",
        "_ownerid_value":  "d431eaf0-ead8-f011-8543-002248384659",
        "statecode":  0,
        "connectionid":  null,
        "_owningteam_value":  null,
        "connectionparametersconfig":  null,
        "modifiedon":  "2025-12-19T12:15:22Z",
        "connectionreferencelogicalname":  "msdyn_sharedsendmail_14119",
        "utcconversiontimezonecode":  null,
        "statuscode":  1,
        "createdon":  "2025-12-19T12:15:22Z"
    },
    {
        "overriddencreatedon":  null,
        "description":  null,
        "timezoneruleversionnumber":  null,
        "componentidunique":  "e015524d-3e29-4c57-a63a-21a76099fff2",
        "promptingbehavior":  0,
        "_owninguser_value":  "d431eaf0-ead8-f011-8543-002248384659",
        "iscustomizable":  {
                               "Value":  true,
                               "CanBeChanged":  true,
                               "ManagedPropertyLogicalName":  "iscustomizableanddeletable"
                           },
        "overwritetime":  "1900-01-01T00:00:00Z",
        "versionnumber":  2534899,
        "_customconnectorid_value":  null,
        "connectionparametersetconfig":  null,
        "importsequencenumber":  null,
        "_modifiedonbehalfby_value":  "4e8c871e-1ed9-f011-8543-002248384659",
        "connectionreferenceid":  "54128e0b-a4d0-4d31-b75a-568844a81444",
        "_createdby_value":  "d431eaf0-ead8-f011-8543-002248384659",
        "componentstate":  0,
        "connectionreferencedisplayname":  "Microsoft Dataverse",
        "ismanaged":  true,
        "_createdonbehalfby_value":  "4e8c871e-1ed9-f011-8543-002248384659",
        "_modifiedby_value":  "d431eaf0-ead8-f011-8543-002248384659",
        "_owningbusinessunit_value":  "e22aeaf0-ead8-f011-8543-002248384659",
        "connectorid":  "/providers/Microsoft.PowerApps/apis/shared_commondataserviceforapps",
        "solutionid":  "60202ef0-9d92-427f-996d-27259e5eba15",
        "@odata.etag":  "W/\"2534899\"",
        "_ownerid_value":  "d431eaf0-ead8-f011-8543-002248384659",
        "statecode":  0,
        "connectionid":  null,
        "_owningteam_value":  null,
        "connectionparametersconfig":  null,
        "modifiedon":  "2025-12-19T12:15:22Z",
        "connectionreferencelogicalname":  "msdyn_sharedcommondataserviceforapps_c00c4",
        "utcconversiontimezonecode":  null,
        "statuscode":  1,
        "createdon":  "2025-12-19T12:15:22Z"
    },
    {
        "overriddencreatedon":  null,
        "description":  null,
        "timezoneruleversionnumber":  null,
        "componentidunique":  "dd1745b9-ce53-4e38-9a6f-f1ca33673cc5",
        "promptingbehavior":  0,
        "_owninguser_value":  "d431eaf0-ead8-f011-8543-002248384659",
        "iscustomizable":  {
                               "Value":  true,
                               "CanBeChanged":  true,
                               "ManagedPropertyLogicalName":  "iscustomizableanddeletable"
                           },
        "overwritetime":  "1900-01-01T00:00:00Z",
        "versionnumber":  2534903,
        "_customconnectorid_value":  null,
        "connectionparametersetconfig":  null,
        "importsequencenumber":  null,
        "_modifiedonbehalfby_value":  "4e8c871e-1ed9-f011-8543-002248384659",
        "connectionreferenceid":  "61aa0520-737d-4459-9f4e-56eb2832d2c2",
        "_createdby_value":  "d431eaf0-ead8-f011-8543-002248384659",
        "componentstate":  0,
        "connectionreferencedisplayname":  "Microsoft Dataverse",
        "ismanaged":  true,
        "_createdonbehalfby_value":  "4e8c871e-1ed9-f011-8543-002248384659",
        "_modifiedby_value":  "d431eaf0-ead8-f011-8543-002248384659",
        "_owningbusinessunit_value":  "e22aeaf0-ead8-f011-8543-002248384659",
        "connectorid":  "/providers/Microsoft.PowerApps/apis/shared_commondataserviceforapps",
        "solutionid":  "60202ef0-9d92-427f-996d-27259e5eba15",
        "@odata.etag":  "W/\"2534903\"",
        "_ownerid_value":  "d431eaf0-ead8-f011-8543-002248384659",
        "statecode":  0,
        "connectionid":  null,
        "_owningteam_value":  null,
        "connectionparametersconfig":  null,
        "modifiedon":  "2025-12-19T12:15:23Z",
        "connectionreferencelogicalname":  "msdynce_sharedcommondataserviceforapps_c282e",
        "utcconversiontimezonecode":  null,
        "statuscode":  1,
        "createdon":  "2025-12-19T12:15:23Z"
    },
    {
        "overriddencreatedon":  null,
        "description":  null,
        "timezoneruleversionnumber":  null,
        "componentidunique":  "1a6a4da0-14d0-4f2d-9e52-22103297099c",
        "promptingbehavior":  0,
        "_owninguser_value":  "358958c0-52b4-4386-8edd-e9b07d4af6d3",
        "iscustomizable":  {
                               "Value":  true,
                               "CanBeChanged":  true,
                               "ManagedPropertyLogicalName":  "iscustomizableanddeletable"
                           },
        "overwritetime":  "1900-01-01T00:00:00Z",
        "versionnumber":  1028067,
        "_customconnectorid_value":  null,
        "connectionparametersetconfig":  null,
        "importsequencenumber":  null,
        "_modifiedonbehalfby_value":  null,
        "connectionreferenceid":  "3d5ae3d1-bad9-49c0-a12e-589b94d3b02c",
        "_createdby_value":  "358958c0-52b4-4386-8edd-e9b07d4af6d3",
        "componentstate":  0,
        "connectionreferencedisplayname":  "Content Conversion",
        "ismanaged":  true,
        "_createdonbehalfby_value":  null,
        "_modifiedby_value":  "358958c0-52b4-4386-8edd-e9b07d4af6d3",
        "_owningbusinessunit_value":  "e22aeaf0-ead8-f011-8543-002248384659",
        "connectorid":  "/providers/Microsoft.PowerApps/apis/shared_conversionservice",
        "solutionid":  "0ad90b79-6955-426e-b85f-5194a0361eb2",
        "@odata.etag":  "W/\"1028067\"",
        "_ownerid_value":  "358958c0-52b4-4386-8edd-e9b07d4af6d3",
        "statecode":  0,
        "connectionid":  null,
        "_owningteam_value":  null,
        "connectionparametersconfig":  null,
        "modifiedon":  "2025-12-14T17:13:18Z",
        "connectionreferencelogicalname":  "msdyn_ContentConversion",
        "utcconversiontimezonecode":  null,
        "statuscode":  1,
        "createdon":  "2025-12-14T17:13:18Z"
    },
    {
        "overriddencreatedon":  null,
        "description":  null,
        "timezoneruleversionnumber":  null,
        "componentidunique":  "c46839a5-3b57-41f2-9d5e-eb40edf85e6b",
        "promptingbehavior":  0,
        "_owninguser_value":  "d431eaf0-ead8-f011-8543-002248384659",
        "iscustomizable":  {
                               "Value":  true,
                               "CanBeChanged":  true,
                               "ManagedPropertyLogicalName":  "iscustomizableanddeletable"
                           },
        "overwritetime":  "1900-01-01T00:00:00Z",
        "versionnumber":  2534901,
        "_customconnectorid_value":  null,
        "connectionparametersetconfig":  null,
        "importsequencenumber":  null,
        "_modifiedonbehalfby_value":  "4e8c871e-1ed9-f011-8543-002248384659",
        "connectionreferenceid":  "af702856-ba98-4211-a308-70d1f6a38be2",
        "_createdby_value":  "d431eaf0-ead8-f011-8543-002248384659",
        "componentstate":  0,
        "connectionreferencedisplayname":  "Mail",
        "ismanaged":  true,
        "_createdonbehalfby_value":  "4e8c871e-1ed9-f011-8543-002248384659",
        "_modifiedby_value":  "d431eaf0-ead8-f011-8543-002248384659",
        "_owningbusinessunit_value":  "e22aeaf0-ead8-f011-8543-002248384659",
        "connectorid":  "/providers/Microsoft.PowerApps/apis/shared_sendmail",
        "solutionid":  "60202ef0-9d92-427f-996d-27259e5eba15",
        "@odata.etag":  "W/\"2534901\"",
        "_ownerid_value":  "d431eaf0-ead8-f011-8543-002248384659",
        "statecode":  0,
        "connectionid":  null,
        "_owningteam_value":  null,
        "connectionparametersconfig":  null,
        "modifiedon":  "2025-12-19T12:15:23Z",
        "connectionreferencelogicalname":  "msdyn_sharedsendmail_5176b",
        "utcconversiontimezonecode":  null,
        "statuscode":  1,
        "createdon":  "2025-12-19T12:15:23Z"
    },
    {
        "overriddencreatedon":  null,
        "description":  null,
        "timezoneruleversionnumber":  null,
        "componentidunique":  "4676c8c4-4c95-462d-878d-4d7947957ee7",
        "promptingbehavior":  0,
        "_owninguser_value":  "d431eaf0-ead8-f011-8543-002248384659",
        "iscustomizable":  {
                               "Value":  true,
                               "CanBeChanged":  true,
                               "ManagedPropertyLogicalName":  "iscustomizableanddeletable"
                           },
        "overwritetime":  "1900-01-01T00:00:00Z",
        "versionnumber":  2534902,
        "_customconnectorid_value":  null,
        "connectionparametersetconfig":  null,
        "importsequencenumber":  null,
        "_modifiedonbehalfby_value":  "4e8c871e-1ed9-f011-8543-002248384659",
        "connectionreferenceid":  "d3e15317-56aa-43d4-9e28-9d648ba48330",
        "_createdby_value":  "d431eaf0-ead8-f011-8543-002248384659",
        "componentstate":  0,
        "connectionreferencedisplayname":  "Mail",
        "ismanaged":  true,
        "_createdonbehalfby_value":  "4e8c871e-1ed9-f011-8543-002248384659",
        "_modifiedby_value":  "d431eaf0-ead8-f011-8543-002248384659",
        "_owningbusinessunit_value":  "e22aeaf0-ead8-f011-8543-002248384659",
        "connectorid":  "/providers/Microsoft.PowerApps/apis/shared_sendmail",
        "solutionid":  "60202ef0-9d92-427f-996d-27259e5eba15",
        "@odata.etag":  "W/\"2534902\"",
        "_ownerid_value":  "d431eaf0-ead8-f011-8543-002248384659",
        "statecode":  0,
        "connectionid":  null,
        "_owningteam_value":  null,
        "connectionparametersconfig":  null,
        "modifiedon":  "2025-12-19T12:15:23Z",
        "connectionreferencelogicalname":  "msdyn_sharedsendmail_65f6b",
        "utcconversiontimezonecode":  null,
        "statuscode":  1,
        "createdon":  "2025-12-19T12:15:23Z"
    },
    {
        "overriddencreatedon":  null,
        "description":  null,
        "timezoneruleversionnumber":  null,
        "componentidunique":  "6728d77f-4d87-42a9-8d09-6f7ffa47e963",
        "promptingbehavior":  0,
        "_owninguser_value":  "d431eaf0-ead8-f011-8543-002248384659",
        "iscustomizable":  {
                               "Value":  true,
                               "CanBeChanged":  true,
                               "ManagedPropertyLogicalName":  "iscustomizableanddeletable"
                           },
        "overwritetime":  "1900-01-01T00:00:00Z",
        "versionnumber":  2534907,
        "_customconnectorid_value":  null,
        "connectionparametersetconfig":  null,
        "importsequencenumber":  null,
        "_modifiedonbehalfby_value":  "4e8c871e-1ed9-f011-8543-002248384659",
        "connectionreferenceid":  "eb8373e2-0306-4ac3-9a67-adfbe32eb817",
        "_createdby_value":  "d431eaf0-ead8-f011-8543-002248384659",
        "componentstate":  0,
        "connectionreferencedisplayname":  "Mail",
        "ismanaged":  true,
        "_createdonbehalfby_value":  "4e8c871e-1ed9-f011-8543-002248384659",
        "_modifiedby_value":  "d431eaf0-ead8-f011-8543-002248384659",
        "_owningbusinessunit_value":  "e22aeaf0-ead8-f011-8543-002248384659",
        "connectorid":  "/providers/Microsoft.PowerApps/apis/shared_sendmail",
        "solutionid":  "60202ef0-9d92-427f-996d-27259e5eba15",
        "@odata.etag":  "W/\"2534907\"",
        "_ownerid_value":  "d431eaf0-ead8-f011-8543-002248384659",
        "statecode":  0,
        "connectionid":  null,
        "_owningteam_value":  null,
        "connectionparametersconfig":  null,
        "modifiedon":  "2025-12-19T12:15:24Z",
        "connectionreferencelogicalname":  "msdynce_sharedsendmail_bdfcf",
        "utcconversiontimezonecode":  null,
        "statuscode":  1,
        "createdon":  "2025-12-19T12:15:24Z"
    },
    {
        "overriddencreatedon":  null,
        "description":  null,
        "timezoneruleversionnumber":  null,
        "componentidunique":  "a9a1554d-50b7-4a89-9425-54ce41903f24",
        "promptingbehavior":  0,
        "_owninguser_value":  "d431eaf0-ead8-f011-8543-002248384659",
        "iscustomizable":  {
                               "Value":  true,
                               "CanBeChanged":  true,
                               "ManagedPropertyLogicalName":  "iscustomizableanddeletable"
                           },
        "overwritetime":  "1900-01-01T00:00:00Z",
        "versionnumber":  2534904,
        "_customconnectorid_value":  null,
        "connectionparametersetconfig":  null,
        "importsequencenumber":  null,
        "_modifiedonbehalfby_value":  "4e8c871e-1ed9-f011-8543-002248384659",
        "connectionreferenceid":  "254c628b-5474-42dc-beff-bd0010c80658",
        "_createdby_value":  "d431eaf0-ead8-f011-8543-002248384659",
        "componentstate":  0,
        "connectionreferencedisplayname":  "Microsoft Dataverse",
        "ismanaged":  true,
        "_createdonbehalfby_value":  "4e8c871e-1ed9-f011-8543-002248384659",
        "_modifiedby_value":  "d431eaf0-ead8-f011-8543-002248384659",
        "_owningbusinessunit_value":  "e22aeaf0-ead8-f011-8543-002248384659",
        "connectorid":  "/providers/Microsoft.PowerApps/apis/shared_commondataserviceforapps",
        "solutionid":  "60202ef0-9d92-427f-996d-27259e5eba15",
        "@odata.etag":  "W/\"2534904\"",
        "_ownerid_value":  "d431eaf0-ead8-f011-8543-002248384659",
        "statecode":  0,
        "connectionid":  null,
        "_owningteam_value":  null,
        "connectionparametersconfig":  null,
        "modifiedon":  "2025-12-19T12:15:23Z",
        "connectionreferencelogicalname":  "msdynce_sharedcommondataserviceforapps_cabe8",
        "utcconversiontimezonecode":  null,
        "statuscode":  1,
        "createdon":  "2025-12-19T12:15:23Z"
    },
    {
        "overriddencreatedon":  null,
        "description":  null,
        "timezoneruleversionnumber":  null,
        "componentidunique":  "a50d4205-fcca-4511-908c-88cb2590ab52",
        "promptingbehavior":  0,
        "_owninguser_value":  "d431eaf0-ead8-f011-8543-002248384659",
        "iscustomizable":  {
                               "Value":  true,
                               "CanBeChanged":  true,
                               "ManagedPropertyLogicalName":  "iscustomizableanddeletable"
                           },
        "overwritetime":  "1900-01-01T00:00:00Z",
        "versionnumber":  2534898,
        "_customconnectorid_value":  null,
        "connectionparametersetconfig":  null,
        "importsequencenumber":  null,
        "_modifiedonbehalfby_value":  "4e8c871e-1ed9-f011-8543-002248384659",
        "connectionreferenceid":  "992905a3-a786-41d1-8511-f90b2f4709c0",
        "_createdby_value":  "d431eaf0-ead8-f011-8543-002248384659",
        "componentstate":  0,
        "connectionreferencedisplayname":  "Microsoft Dataverse",
        "ismanaged":  true,
        "_createdonbehalfby_value":  "4e8c871e-1ed9-f011-8543-002248384659",
        "_modifiedby_value":  "d431eaf0-ead8-f011-8543-002248384659",
        "_owningbusinessunit_value":  "e22aeaf0-ead8-f011-8543-002248384659",
        "connectorid":  "/providers/Microsoft.PowerApps/apis/shared_commondataserviceforapps",
        "solutionid":  "60202ef0-9d92-427f-996d-27259e5eba15",
        "@odata.etag":  "W/\"2534898\"",
        "_ownerid_value":  "d431eaf0-ead8-f011-8543-002248384659",
        "statecode":  0,
        "connectionid":  null,
        "_owningteam_value":  null,
        "connectionparametersconfig":  null,
        "modifiedon":  "2025-12-19T12:15:22Z",
        "connectionreferencelogicalname":  "msdyn_sharedcommondataserviceforapps_220ed",
        "utcconversiontimezonecode":  null,
        "statuscode":  1,
        "createdon":  "2025-12-19T12:15:22Z"
    }
]
